[
    {
        "id": "1",
        "catalogo": "Catalogo 2",
        "pid": "10172",
        "nombre": "GoogleCrashHandler64.exe",
        "usuario": "Services",
        "prioridad": "0",
        "memoria": "56",
        "iteraciones": 0,
        "tiempoLlegada": -1,
        "tiempoFin": 0,
        "estado": "Esperando"
    },
    {
        "id": "2",
        "catalogo": "Catalogo 2",
        "pid": "1596",
        "nombre": "GoogleCrashHandler.exe",
        "usuario": "Services",
        "prioridad": "0",
        "memoria": "84",
        "iteraciones": 0,
        "tiempoLlegada": -1,
        "tiempoFin": 0,
        "estado": "Esperando"
    },
    {
        "id": "3",
        "catalogo": "Catalogo 2",
        "pid": "496",
        "nombre": "smss.exe",
        "usuario": "Services",
        "prioridad": "0",
        "memoria": "1.240",
        "iteraciones": 0,
        "tiempoLlegada": -1,
        "tiempoFin": 0,
        "estado": "Esperando"
    },
    {
        "id": "4",
        "catalogo": "Catalogo 2",
        "pid": "10936",
        "nombre": "SystemSettings.exe",
        "usuario": "Console",
        "prioridad": "1",
        "memoria": "1.572",
        "iteraciones": 0,
        "tiempoLlegada": -1,
        "tiempoFin": 0,
        "estado": "Esperando"
    },
    {
        "id": "5",
        "catalogo": "Catalogo 2",
        "pid": "6004",
        "nombre": "HostAppServiceUpdater.exe",
        "usuario": "Console",
        "prioridad": "1",
        "memoria": "2.476",
        "iteraciones": 0,
        "tiempoLlegada": -1,
        "tiempoFin": 0,
        "estado": "Esperando"
    }
]